{
  "generatedAt": "2026-07-02T23:35:07.833Z",
  "source": {
    "sourceKind": "multi-dashboard-local",
    "workspacePath": "D:\\web\\multi-dashboard",
    "inventoryPath": "D:\\web\\multi-dashboard\\data\\monetization\\affiliates\\inventory.yml",
    "merchantsPath": "D:\\web\\multi-dashboard\\data\\monetization\\affiliates\\ripplealba-merchants.yml",
    "analysisPath": "D:\\web\\multi-dashboard\\data\\monetization\\affiliates\\ripplealba-analysis.md",
    "inventoryExists": true,
    "merchantsExists": true,
    "inventoryUpdatedAt": "2026-07-02T23:34:41.550Z",
    "merchantsUpdatedAt": "2026-07-02T03:52:03.308Z",
    "sourceNote": "Standalone affiliate operations source owned by this multi-dashboard repository."
  },
  "sourcePolicy": "metadata_only",
  "lastManualSync": "2026-07-03",
  "programs": [
    {
      "id": "coupang-partners",
      "name": "Coupang Partners",
      "status": "candidate",
      "priority": "p0",
      "region": "KR",
      "network": "Coupang",
      "category": "ecommerce",
      "platformUrl": "https://partners.coupang.com/",
      "homepageUrl": "https://partners.coupang.com/",
      "applyUrl": "https://partners.coupang.com/",
      "sourceUrl": "https://partners.coupangcdn.com/partners-guide/partners-guide-20240716100922.pdf",
      "countries": [
        "KR"
      ],
      "usedBySites": [],
      "usedByAppsInToss": [],
      "publicTrackingLabel": "coupang-partners",
      "disclosureRequired": true,
      "disclosureNote": "Korean economic-interest disclosure must be close to the recommendation/link.",
      "monetizationModel": "Product deep links, short links, and display/banner creatives.",
      "payoutModel": "CPS; official guide has stated 3% on eligible transaction amount, but verify current category terms before publishing.",
      "approvalDifficulty": "low",
      "bannerSuitability": "high",
      "deepLinkTemplate": "Generate inside Coupang Partners; do not hand-build tracking URLs.",
      "contentFit": [
        "shopping guides",
        "product reviews",
        "household, beauty, baby, electronics, seasonal deals"
      ],
      "recommendedSlots": [
        "article-mid-728x90",
        "after-content-728x90",
        "mobile-inline-320x100"
      ],
      "allowedSites": [],
      "risk": "medium",
      "complianceNotes": [
        "Use clear Korean affiliate disclosure near each recommendation.",
        "Use rel=sponsored nofollow for links.",
        "Verify current commission, cookie, prohibited traffic, and API rules in the account."
      ],
      "merchantTotalReported": 0,
      "merchantSnapshotFile": "",
      "lastReviewed": "2026-07-03",
      "nextAction": "Apply or confirm existing account, create site/channel list, then create first product-review banner link.",
      "notes": "Best first Korean commerce candidate for broad content sites."
    },
    {
      "id": "coupang-influencers",
      "name": "Coupang Influencers",
      "status": "candidate",
      "priority": "p1",
      "region": "KR",
      "network": "Coupang",
      "category": "creator_commerce",
      "platformUrl": "https://influencers.coupang.com/",
      "homepageUrl": "https://influencers.coupang.com/",
      "applyUrl": "https://influencers.coupang.com/",
      "sourceUrl": "https://influencers.coupang.com/",
      "countries": [
        "KR"
      ],
      "usedBySites": [],
      "usedByAppsInToss": [],
      "publicTrackingLabel": "coupang-influencers",
      "disclosureRequired": true,
      "disclosureNote": "Show paid/affiliate relationship clearly.",
      "monetizationModel": "Creator storefront and recommended product links.",
      "payoutModel": "Base commission plus time-limited promotions may apply; verify inside program.",
      "approvalDifficulty": "medium",
      "bannerSuitability": "medium",
      "deepLinkTemplate": "Use Coupang Influencers store/product links generated by the platform.",
      "contentFit": [
        "creator-style recommendations",
        "curated shopping lists",
        "social-friendly product collections"
      ],
      "recommendedSlots": [
        "after-content-728x90",
        "mobile-inline-320x100"
      ],
      "allowedSites": [],
      "risk": "medium",
      "complianceNotes": [
        "Use only approved channels and generated links.",
        "Verify promotion terms before showing bonus rates."
      ],
      "merchantTotalReported": 0,
      "merchantSnapshotFile": "",
      "lastReviewed": "2026-07-03",
      "nextAction": "Verify eligibility and whether site-owned channels can use this program.",
      "notes": "Good for shopping persona pages after basic Coupang Partners is live."
    },
    {
      "id": "naver-shopping-connect",
      "name": "Naver Shopping Connect",
      "status": "candidate",
      "priority": "p1",
      "region": "KR",
      "network": "Naver Brand Connect",
      "category": "ecommerce",
      "platformUrl": "https://solution.smartstore.naver.com/ko/detail/7BxhKW54rdxqi9m4N3fNcZ",
      "homepageUrl": "https://solution.smartstore.naver.com/ko/detail/7BxhKW54rdxqi9m4N3fNcZ",
      "applyUrl": "https://brandconnect.naver.com/",
      "sourceUrl": "https://www.navercorp.com/media/pressReleasesDetail?seq=33116",
      "countries": [
        "KR"
      ],
      "usedBySites": [],
      "usedByAppsInToss": [],
      "publicTrackingLabel": "naver-shopping-connect",
      "disclosureRequired": true,
      "disclosureNote": "Korean economic-interest disclosure required.",
      "monetizationModel": "SmartStore creator affiliate links through Brand Connect/Shopping Connect.",
      "payoutModel": "Revenue-share set by participating sellers/products; verify each product offer.",
      "approvalDifficulty": "medium",
      "bannerSuitability": "medium",
      "deepLinkTemplate": "Use Shopping Connect generated links; do not replace seller/product parameters.",
      "contentFit": [
        "Naver-facing product recommendation",
        "beauty, living, parenting, food, local shopping"
      ],
      "recommendedSlots": [
        "article-mid-728x90",
        "mobile-inline-320x100"
      ],
      "allowedSites": [],
      "risk": "medium",
      "complianceNotes": [
        "Product-level terms vary by seller.",
        "Keep recommendation content specific to the product/store being promoted."
      ],
      "merchantTotalReported": 0,
      "merchantSnapshotFile": "",
      "lastReviewed": "2026-07-03",
      "nextAction": "Confirm creator/channel eligibility and collect product-level revenue share.",
      "notes": "Useful where Naver search or SmartStore intent is high."
    },
    {
      "id": "naver-brand-connect",
      "name": "Naver Brand Connect",
      "status": "manual_review",
      "priority": "manual",
      "region": "KR",
      "network": "Naver Brand Connect",
      "category": "creator_campaigns",
      "platformUrl": "https://help.naver.com/service/30027/contents/22979?lang=ko&osType=COMMONOS",
      "homepageUrl": "https://help.naver.com/service/30027/contents/22979?lang=ko&osType=COMMONOS",
      "applyUrl": "https://brandconnect.naver.com/",
      "sourceUrl": "https://help.naver.com/service/30027/contents/23408?lang=ko&osType=COMMONOS",
      "countries": [
        "KR"
      ],
      "usedBySites": [],
      "usedByAppsInToss": [],
      "publicTrackingLabel": "naver-brand-connect",
      "disclosureRequired": true,
      "disclosureNote": "Campaign sponsorship/economic-interest disclosure required.",
      "monetizationModel": "Creator campaign and sponsored partnership flow, separate from open affiliate deep links.",
      "payoutModel": "Campaign or negotiated settlement; verify per campaign before publishing.",
      "approvalDifficulty": "high",
      "bannerSuitability": "low",
      "deepLinkTemplate": "Use campaign-provided links only after approval.",
      "contentFit": [
        "creator collaborations",
        "sponsored editorial",
        "Naver Blog, Instagram, YouTube channel campaigns"
      ],
      "recommendedSlots": [
        "after-content-728x90"
      ],
      "allowedSites": [],
      "risk": "high",
      "complianceNotes": [
        "Not a general self-serve affiliate network for every owned site.",
        "Each campaign can define channel, wording, and settlement restrictions."
      ],
      "merchantTotalReported": 0,
      "merchantSnapshotFile": "",
      "lastReviewed": "2026-07-03",
      "nextAction": "Keep as manual-review campaign source; do not wire as a normal banner affiliate until campaign terms are approved.",
      "notes": "Useful for campaign monetization, but should not be mixed with auto banner rotation."
    },
    {
      "id": "naver-shopping-live",
      "name": "Naver Shopping Live Partnership",
      "status": "manual_review",
      "priority": "manual",
      "region": "KR",
      "network": "Naver",
      "category": "live_commerce",
      "platformUrl": "https://help.naver.com/service/21349/contents/14569?lang=ko",
      "homepageUrl": "https://help.naver.com/service/21349/contents/14569?lang=ko",
      "applyUrl": "https://help.naver.com/service/21349/contents/14569?lang=ko",
      "sourceUrl": "https://help.naver.com/service/21349/contents/14570?lang=ko",
      "countries": [
        "KR"
      ],
      "usedBySites": [],
      "usedByAppsInToss": [],
      "publicTrackingLabel": "naver-shopping-live",
      "disclosureRequired": true,
      "disclosureNote": "Sponsored/live-commerce relationship must be disclosed.",
      "monetizationModel": "Proposal-based live-commerce partnership.",
      "payoutModel": "Negotiated per live event or campaign; verify manually.",
      "approvalDifficulty": "high",
      "bannerSuitability": "low",
      "deepLinkTemplate": "Use approved live-event URLs only.",
      "contentFit": [
        "launch events",
        "seasonal live deals",
        "brand collaboration pages"
      ],
      "recommendedSlots": [
        "after-content-728x90"
      ],
      "allowedSites": [],
      "risk": "high",
      "complianceNotes": [
        "Do not present as an open affiliate program.",
        "Remove or expire banners after event end dates."
      ],
      "merchantTotalReported": 0,
      "merchantSnapshotFile": "",
      "lastReviewed": "2026-07-03",
      "nextAction": "Treat as proposal-only monetization; create banners only after event approval and date validation.",
      "notes": "Manual live-commerce option for event pages, not evergreen affiliate inventory."
    },
    {
      "id": "naver-adpost",
      "name": "Naver AdPost",
      "status": "manual_review",
      "priority": "manual",
      "region": "KR",
      "network": "Naver",
      "category": "display_ads",
      "platformUrl": "https://adpost.naver.com/",
      "homepageUrl": "https://adpost.naver.com/",
      "applyUrl": "https://adpost.naver.com/",
      "sourceUrl": "https://help.naver.com/support/contents/contents.help?categoryNo=9418&serviceNo=726",
      "countries": [
        "KR"
      ],
      "usedBySites": [],
      "usedByAppsInToss": [],
      "publicTrackingLabel": "naver-adpost",
      "disclosureRequired": false,
      "disclosureNote": "Ad platform disclosure differs from affiliate endorsement disclosure.",
      "monetizationModel": "Naver media ad revenue share, not a normal off-site affiliate program.",
      "payoutModel": "Revenue share from ads shown/clicked on eligible Naver media; criteria are controlled by Naver.",
      "approvalDifficulty": "high",
      "bannerSuitability": "low",
      "deepLinkTemplate": "Not applicable to this dashboard's banner redirect system.",
      "contentFit": [
        "Naver Blog/Cafe media",
        "Naver ecosystem content"
      ],
      "recommendedSlots": [],
      "allowedSites": [],
      "risk": "high",
      "complianceNotes": [
        "Keep separate from affiliate link management.",
        "Eligibility and revenue share are platform-controlled."
      ],
      "merchantTotalReported": 0,
      "merchantSnapshotFile": "",
      "lastReviewed": "2026-07-03",
      "nextAction": "Track as a Naver media monetization option, but do not wire into banner redirects.",
      "notes": "Included for completeness; not a banner item for owned Next.js/WordPress sites."
    },
    {
      "id": "linkprice",
      "name": "LinkPrice",
      "status": "candidate",
      "priority": "p1",
      "region": "KR",
      "network": "LinkPrice",
      "category": "affiliate_network",
      "platformUrl": "https://www.linkprice.com/",
      "homepageUrl": "https://www.linkprice.com/",
      "applyUrl": "https://www.linkprice.com/",
      "sourceUrl": "https://www.linkprice.com/",
      "countries": [
        "KR"
      ],
      "usedBySites": [],
      "usedByAppsInToss": [],
      "publicTrackingLabel": "linkprice",
      "disclosureRequired": true,
      "disclosureNote": "Affiliate/ad disclosure required near promotional content.",
      "monetizationModel": "Korean affiliate network for CPS/CPL/CPC merchant campaigns.",
      "payoutModel": "Varies by merchant and campaign; verify per offer.",
      "approvalDifficulty": "medium",
      "bannerSuitability": "high",
      "deepLinkTemplate": "Use LinkPrice tracking/deep-link builder per merchant.",
      "contentFit": [
        "shopping, travel, finance, education, subscription services",
        "Korea-focused comparison pages"
      ],
      "recommendedSlots": [
        "sidebar-300x250",
        "after-content-728x90"
      ],
      "allowedSites": [],
      "risk": "medium",
      "complianceNotes": [
        "Merchant terms vary; collect landing URL, allowed media, and prohibited keywords.",
        "Be alert for impersonation/phishing warnings; only use official login/domain."
      ],
      "merchantTotalReported": 0,
      "merchantSnapshotFile": "",
      "lastReviewed": "2026-07-03",
      "nextAction": "Apply and export merchant list by site category; avoid high-risk finance/medical offers until review.",
      "notes": "Good network layer after first direct programs."
    },
    {
      "id": "tenping",
      "name": "Tenping",
      "status": "candidate",
      "priority": "p2",
      "region": "KR",
      "network": "Tenping",
      "category": "affiliate_network",
      "platformUrl": "https://tenping.kr/",
      "homepageUrl": "https://tenping.kr/",
      "applyUrl": "https://tenping.kr/",
      "sourceUrl": "https://tenping.kr/",
      "countries": [
        "KR"
      ],
      "usedBySites": [],
      "usedByAppsInToss": [],
      "publicTrackingLabel": "tenping",
      "disclosureRequired": true,
      "disclosureNote": "Show economic-interest disclosure clearly.",
      "monetizationModel": "Campaign links generated from Tenping for blog/SNS promotion.",
      "payoutModel": "Varies by campaign; verify offer terms before publication.",
      "approvalDifficulty": "medium",
      "bannerSuitability": "medium",
      "deepLinkTemplate": "Use Tenping generated promotion URL.",
      "contentFit": [
        "viral content",
        "campaign-specific CPA offers",
        "SNS/blog mixed traffic"
      ],
      "recommendedSlots": [
        "after-content-728x90",
        "mobile-inline-320x100"
      ],
      "allowedSites": [],
      "risk": "high",
      "complianceNotes": [
        "CPA campaigns can carry aggressive claims; review copy manually.",
        "Do not use sensitive offers without legal/policy review."
      ],
      "merchantTotalReported": 0,
      "merchantSnapshotFile": "",
      "lastReviewed": "2026-07-03",
      "nextAction": "Use only after campaign compliance review and landing page quality check.",
      "notes": "Useful but should be gated behind stricter campaign review."
    },
    {
      "id": "amazon-associates",
      "name": "Amazon Associates",
      "status": "candidate",
      "priority": "p0",
      "region": "GLOBAL",
      "network": "Amazon",
      "category": "ecommerce",
      "platformUrl": "https://affiliate-program.amazon.com/",
      "homepageUrl": "https://affiliate-program.amazon.com/",
      "applyUrl": "https://affiliate-program.amazon.com/",
      "sourceUrl": "https://affiliate-program.amazon.com/help/operating/policies",
      "countries": [
        "US",
        "GLOBAL"
      ],
      "usedBySites": [],
      "usedByAppsInToss": [],
      "publicTrackingLabel": "amazon-associates",
      "disclosureRequired": true,
      "disclosureNote": "Amazon requires clear associate identification and legally compliant disclosure.",
      "monetizationModel": "Product links, Native Shopping Ads, banners, and store/product recommendations.",
      "payoutModel": "Category-based standard commission income on qualifying purchases; verify current rate table.",
      "approvalDifficulty": "medium",
      "bannerSuitability": "high",
      "deepLinkTemplate": "Use SiteStripe or Amazon Associates link generator with correct tracking tag.",
      "contentFit": [
        "English product reviews",
        "software/hardware buying guides",
        "global shopping posts"
      ],
      "recommendedSlots": [
        "article-mid-728x90",
        "after-content-728x90",
        "mobile-inline-320x100"
      ],
      "allowedSites": [],
      "risk": "medium",
      "complianceNotes": [
        "Do not cloak or alter Amazon links outside allowed tools.",
        "Display Amazon-required associate disclosure where applicable.",
        "Verify use of images/prices through approved tools/API."
      ],
      "merchantTotalReported": 0,
      "merchantSnapshotFile": "",
      "lastReviewed": "2026-07-03",
      "nextAction": "Apply with English/global sites and add required Amazon Associate disclosure text.",
      "notes": "Best global ecommerce baseline."
    },
    {
      "id": "ebay-partner-network",
      "name": "eBay Partner Network",
      "status": "candidate",
      "priority": "p1",
      "region": "GLOBAL",
      "network": "eBay",
      "category": "ecommerce_marketplace",
      "platformUrl": "https://partnernetwork.ebay.com/",
      "homepageUrl": "https://partnernetwork.ebay.com/",
      "applyUrl": "https://partnernetwork.ebay.com/",
      "sourceUrl": "https://partnernetwork.ebay.com/our-program/rate-card",
      "countries": [
        "US",
        "GLOBAL"
      ],
      "usedBySites": [],
      "usedByAppsInToss": [],
      "publicTrackingLabel": "ebay-partner-network",
      "disclosureRequired": true,
      "disclosureNote": "Affiliate disclosure required.",
      "monetizationModel": "Listing/category links, campaigns, and marketplace banners.",
      "payoutModel": "Percentage of qualifying transaction GMB by category; caps may apply.",
      "approvalDifficulty": "medium",
      "bannerSuitability": "medium",
      "deepLinkTemplate": "Use EPN link generator or API/campaign tools.",
      "contentFit": [
        "collectibles",
        "used/refurbished products",
        "parts, niche gear, comparison content"
      ],
      "recommendedSlots": [
        "article-mid-728x90",
        "after-content-728x90"
      ],
      "allowedSites": [],
      "risk": "medium",
      "complianceNotes": [
        "Review rate caps and prohibited traffic.",
        "Avoid misleading discount/voucher claims."
      ],
      "merchantTotalReported": 0,
      "merchantSnapshotFile": "",
      "lastReviewed": "2026-07-03",
      "nextAction": "Apply for global shopping/niche product sites after Amazon/Coupang baseline.",
      "notes": "Strong for niche and long-tail commerce articles."
    },
    {
      "id": "booking-affiliates",
      "name": "Booking.com Affiliate Partner Program",
      "status": "candidate",
      "priority": "p1",
      "region": "GLOBAL",
      "network": "Booking.com / affiliate networks",
      "category": "travel",
      "platformUrl": "https://www.booking.com/affiliate-program/v2/index.html",
      "homepageUrl": "https://www.booking.com/affiliate-program/v2/index.html",
      "applyUrl": "https://www.booking.com/affiliate-program/v2/index.html",
      "sourceUrl": "https://www.booking.com/affiliate-program/v2/index.html",
      "countries": [
        "GLOBAL"
      ],
      "usedBySites": [],
      "usedByAppsInToss": [],
      "publicTrackingLabel": "booking-affiliates",
      "disclosureRequired": true,
      "disclosureNote": "Affiliate disclosure required near travel recommendations.",
      "monetizationModel": "Travel accommodation search boxes, links, widgets, and banners.",
      "payoutModel": "Commission on eligible completed travel bookings; exact rate/network terms vary.",
      "approvalDifficulty": "medium",
      "bannerSuitability": "high",
      "deepLinkTemplate": "Use Booking.com partner tools or network tracking links.",
      "contentFit": [
        "travel guides",
        "city itineraries",
        "hotel comparisons"
      ],
      "recommendedSlots": [
        "after-content-728x90",
        "sidebar-300x250"
      ],
      "allowedSites": [],
      "risk": "medium",
      "complianceNotes": [
        "Do not claim unavailable discounts.",
        "Use truthful availability/ranking language."
      ],
      "merchantTotalReported": 0,
      "merchantSnapshotFile": "",
      "lastReviewed": "2026-07-03",
      "nextAction": "Use only on travel-intent sites/pages; configure city/deep-link templates per article.",
      "notes": "Good match for travel and local guide inventory."
    },
    {
      "id": "impact-marketplace",
      "name": "impact.com Marketplace",
      "status": "candidate",
      "priority": "p1",
      "region": "GLOBAL",
      "network": "impact.com",
      "category": "affiliate_network",
      "platformUrl": "https://impact.com/partners/",
      "homepageUrl": "https://impact.com/partners/",
      "applyUrl": "https://impact.com/partners/",
      "sourceUrl": "https://impact.com/partners/",
      "countries": [
        "GLOBAL"
      ],
      "usedBySites": [],
      "usedByAppsInToss": [],
      "publicTrackingLabel": "impact-marketplace",
      "disclosureRequired": true,
      "disclosureNote": "Affiliate disclosure required; advertiser terms can add wording.",
      "monetizationModel": "Brand partnerships, affiliate links, promo assets, and publisher reporting.",
      "payoutModel": "Varies by advertiser contract.",
      "approvalDifficulty": "medium",
      "bannerSuitability": "high",
      "deepLinkTemplate": "Use impact.com tracking link/deep-link builder per joined advertiser.",
      "contentFit": [
        "software",
        "commerce",
        "finance-safe comparisons",
        "premium brand reviews"
      ],
      "recommendedSlots": [
        "sidebar-300x250",
        "after-content-728x90"
      ],
      "allowedSites": [],
      "risk": "medium",
      "complianceNotes": [
        "Each advertiser has separate approval and promotional restrictions.",
        "Store advertiser IDs and terms before enabling banners."
      ],
      "merchantTotalReported": 0,
      "merchantSnapshotFile": "",
      "lastReviewed": "2026-07-03",
      "nextAction": "Create publisher profile and shortlist brands by site category.",
      "notes": "Best global network layer for diverse sites."
    },
    {
      "id": "cj-affiliate",
      "name": "CJ Affiliate",
      "status": "candidate",
      "priority": "p1",
      "region": "GLOBAL",
      "network": "CJ",
      "category": "affiliate_network",
      "platformUrl": "https://www.cj.com/publisher",
      "homepageUrl": "https://www.cj.com/publisher",
      "applyUrl": "https://signup.cj.com/member/signup/publisher/",
      "sourceUrl": "https://www.cj.com/publisher",
      "countries": [
        "GLOBAL"
      ],
      "usedBySites": [],
      "usedByAppsInToss": [],
      "publicTrackingLabel": "cj-affiliate",
      "disclosureRequired": true,
      "disclosureNote": "Affiliate disclosure required; advertiser terms may add restrictions.",
      "monetizationModel": "Publisher network links, brand programs, widgets, and creatives.",
      "payoutModel": "Varies by advertiser.",
      "approvalDifficulty": "high",
      "bannerSuitability": "high",
      "deepLinkTemplate": "Use CJ deep links and advertiser creatives after approval.",
      "contentFit": [
        "established content sites",
        "shopping, finance-safe, software, travel"
      ],
      "recommendedSlots": [
        "sidebar-300x250",
        "after-content-728x90"
      ],
      "allowedSites": [],
      "risk": "medium",
      "complianceNotes": [
        "Expect advertiser-by-advertiser approval.",
        "Avoid unsupported coupon/voucher claims."
      ],
      "merchantTotalReported": 0,
      "merchantSnapshotFile": "",
      "lastReviewed": "2026-07-03",
      "nextAction": "Apply after preparing traffic proof and site category descriptions.",
      "notes": "Selective but strong once sites have traffic and clear niches."
    },
    {
      "id": "awin",
      "name": "Awin",
      "status": "candidate",
      "priority": "p1",
      "region": "GLOBAL",
      "network": "Awin",
      "category": "affiliate_network",
      "platformUrl": "https://www.awin.com/",
      "homepageUrl": "https://www.awin.com/",
      "applyUrl": "https://www.awin.com/us/pricing/affiliate-partners",
      "sourceUrl": "https://www.awin.com/us/pricing/affiliate-partners",
      "countries": [
        "US",
        "UK",
        "EU",
        "GLOBAL"
      ],
      "usedBySites": [],
      "usedByAppsInToss": [],
      "publicTrackingLabel": "awin",
      "disclosureRequired": true,
      "disclosureNote": "Affiliate disclosure required.",
      "monetizationModel": "Affiliate links across brand advertisers and publisher reporting.",
      "payoutModel": "Varies by advertiser; publisher signup advertised as no cost.",
      "approvalDifficulty": "medium",
      "bannerSuitability": "high",
      "deepLinkTemplate": "Use Awin link builder per joined advertiser.",
      "contentFit": [
        "commerce",
        "software",
        "fashion/lifestyle",
        "international content"
      ],
      "recommendedSlots": [
        "sidebar-300x250",
        "after-content-728x90"
      ],
      "allowedSites": [],
      "risk": "medium",
      "complianceNotes": [
        "Advertiser terms vary.",
        "Confirm whether each brand supports your country/site."
      ],
      "merchantTotalReported": 0,
      "merchantSnapshotFile": "",
      "lastReviewed": "2026-07-03",
      "nextAction": "Apply and map advertisers to site categories; treat ShareASale legacy programs under Awin where applicable.",
      "notes": "Broad global network for non-Korean programs."
    },
    {
      "id": "rakuten-advertising",
      "name": "Rakuten Advertising",
      "status": "candidate",
      "priority": "p2",
      "region": "GLOBAL",
      "network": "Rakuten Advertising",
      "category": "affiliate_network",
      "platformUrl": "https://rakutenadvertising.com/publishers/",
      "homepageUrl": "https://rakutenadvertising.com/publishers/",
      "applyUrl": "https://rakutenadvertising.com/publishers/",
      "sourceUrl": "https://pubhelp.rakutenadvertising.com/hc/en-us/articles/360059970591-Affiliate-Marketing-101-Video",
      "countries": [
        "GLOBAL"
      ],
      "usedBySites": [],
      "usedByAppsInToss": [],
      "publicTrackingLabel": "rakuten-advertising",
      "disclosureRequired": true,
      "disclosureNote": "Affiliate disclosure required.",
      "monetizationModel": "Publisher network programs and creatives.",
      "payoutModel": "Varies by advertiser.",
      "approvalDifficulty": "medium",
      "bannerSuitability": "high",
      "deepLinkTemplate": "Use Rakuten network tracking tools after approval.",
      "contentFit": [
        "premium brands",
        "shopping",
        "lifestyle",
        "global content"
      ],
      "recommendedSlots": [
        "sidebar-300x250",
        "after-content-728x90"
      ],
      "allowedSites": [],
      "risk": "medium",
      "complianceNotes": [
        "Advertiser approvals and countries differ.",
        "Collect terms before enabling banners."
      ],
      "merchantTotalReported": 0,
      "merchantSnapshotFile": "",
      "lastReviewed": "2026-07-03",
      "nextAction": "Apply after P0/P1 networks or where a target brand exists only on Rakuten.",
      "notes": "Useful for premium brand coverage."
    },
    {
      "id": "partnerstack-marketplace",
      "name": "PartnerStack Marketplace",
      "status": "candidate",
      "priority": "p1",
      "region": "GLOBAL",
      "network": "PartnerStack",
      "category": "b2b_saas",
      "platformUrl": "https://market.partnerstack.com/",
      "homepageUrl": "https://partnerstack.com/",
      "applyUrl": "https://market.partnerstack.com/",
      "sourceUrl": "https://partnerstack.com/",
      "countries": [
        "GLOBAL"
      ],
      "usedBySites": [],
      "usedByAppsInToss": [],
      "publicTrackingLabel": "partnerstack",
      "disclosureRequired": true,
      "disclosureNote": "Affiliate disclosure required.",
      "monetizationModel": "B2B SaaS affiliate/referral marketplace.",
      "payoutModel": "Varies by vendor; may include fixed bounty and/or revenue share.",
      "approvalDifficulty": "medium",
      "bannerSuitability": "medium",
      "deepLinkTemplate": "Use PartnerStack vendor-specific tracking links.",
      "contentFit": [
        "AI tools",
        "business software",
        "productivity",
        "marketing operations"
      ],
      "recommendedSlots": [
        "sidebar-300x250",
        "after-content-728x90"
      ],
      "allowedSites": [],
      "risk": "medium",
      "complianceNotes": [
        "Vendor programs can close or pause.",
        "Verify allowed bidding/email/coupon terms."
      ],
      "merchantTotalReported": 0,
      "merchantSnapshotFile": "",
      "lastReviewed": "2026-07-03",
      "nextAction": "Shortlist SaaS offers that match AI/business/tool sites.",
      "notes": "Good for tool-review and AI/software sites."
    },
    {
      "id": "shopify-affiliates",
      "name": "Shopify Affiliate Program",
      "status": "candidate",
      "priority": "p1",
      "region": "GLOBAL",
      "network": "Shopify",
      "category": "ecommerce_saas",
      "platformUrl": "https://www.shopify.com/affiliates",
      "homepageUrl": "https://www.shopify.com/affiliates",
      "applyUrl": "https://www.shopify.com/affiliates",
      "sourceUrl": "https://help.shopify.com/en/affiliates/about",
      "countries": [
        "GLOBAL"
      ],
      "usedBySites": [],
      "usedByAppsInToss": [],
      "publicTrackingLabel": "shopify-affiliates",
      "disclosureRequired": true,
      "disclosureNote": "Affiliate disclosure required.",
      "monetizationModel": "Referral link for new merchants signing up for paid Shopify plans.",
      "payoutModel": "Commission on eligible paid merchant referrals; verify current terms.",
      "approvalDifficulty": "medium",
      "bannerSuitability": "medium",
      "deepLinkTemplate": "Use Shopify affiliate referral link generated after approval.",
      "contentFit": [
        "online business",
        "smart seller",
        "ecommerce setup",
        "side-hustle guides"
      ],
      "recommendedSlots": [
        "after-content-728x90",
        "sidebar-300x250"
      ],
      "allowedSites": [],
      "risk": "medium",
      "complianceNotes": [
        "Do not promise income outcomes.",
        "Use current plan/pricing facts only."
      ],
      "merchantTotalReported": 0,
      "merchantSnapshotFile": "",
      "lastReviewed": "2026-07-03",
      "nextAction": "Match to seller/ecommerce sites and create tutorial CTAs.",
      "notes": "Strong SaaS affiliate for ecommerce education content."
    },
    {
      "id": "hubspot-affiliates",
      "name": "HubSpot Affiliate Program",
      "status": "candidate",
      "priority": "p0",
      "region": "GLOBAL",
      "network": "HubSpot",
      "category": "b2b_saas",
      "platformUrl": "https://www.hubspot.com/partners/affiliates",
      "homepageUrl": "https://www.hubspot.com/partners/affiliates",
      "applyUrl": "https://www.hubspot.com/partners/affiliates",
      "sourceUrl": "https://www.hubspot.com/company-news/hubspot-launches-its-revamped-affiliate-program",
      "countries": [
        "GLOBAL"
      ],
      "usedBySites": [],
      "usedByAppsInToss": [],
      "publicTrackingLabel": "hubspot-affiliates",
      "disclosureRequired": true,
      "disclosureNote": "Affiliate disclosure required near recommendations.",
      "monetizationModel": "Referral links for CRM, marketing, sales, and business software audiences.",
      "payoutModel": "Public program materials have described 30% recurring commission up to 12 months; verify current terms before publication.",
      "approvalDifficulty": "medium",
      "bannerSuitability": "high",
      "deepLinkTemplate": "Use HubSpot affiliate tracking link generated after approval.",
      "contentFit": [
        "CRM comparisons",
        "B2B marketing",
        "sales operations",
        "startup tooling"
      ],
      "recommendedSlots": [
        "sidebar-300x250",
        "after-content-728x90",
        "article-mid-728x90"
      ],
      "allowedSites": [],
      "risk": "medium",
      "complianceNotes": [
        "Do not confuse affiliate program with HubSpot solutions partner status.",
        "Verify current recurring commission and paid-plan eligibility in account terms."
      ],
      "merchantTotalReported": 0,
      "merchantSnapshotFile": "",
      "lastReviewed": "2026-07-03",
      "nextAction": "Apply for B2B/software sites and prepare CRM comparison CTAs after approval.",
      "notes": "High-value B2B SaaS candidate for CRM and marketing content."
    },
    {
      "id": "notion-affiliates",
      "name": "Notion Affiliate Program",
      "status": "manual_review",
      "priority": "p2",
      "region": "GLOBAL",
      "network": "Notion / PartnerStack",
      "category": "productivity_saas",
      "platformUrl": "https://www.notion.com/affiliates",
      "homepageUrl": "https://www.notion.com/affiliates",
      "applyUrl": "https://www.notion.com/affiliates",
      "sourceUrl": "https://www.notion.com/affiliates",
      "countries": [
        "GLOBAL"
      ],
      "usedBySites": [],
      "usedByAppsInToss": [],
      "publicTrackingLabel": "notion-affiliates",
      "disclosureRequired": true,
      "disclosureNote": "Affiliate disclosure required.",
      "monetizationModel": "Activated signup bounty and first-year revenue share where available.",
      "payoutModel": "Official page states up to $50 per activated signup plus 20% of year-one revenue; verify current availability.",
      "approvalDifficulty": "high",
      "bannerSuitability": "medium",
      "deepLinkTemplate": "Use PartnerStack/Notion generated links only.",
      "contentFit": [
        "productivity templates",
        "AI workflow",
        "study/business organization"
      ],
      "recommendedSlots": [
        "after-content-728x90",
        "sidebar-300x250"
      ],
      "allowedSites": [],
      "risk": "high",
      "complianceNotes": [
        "Program availability may change.",
        "Do not show payout claims unless verified in current application dashboard."
      ],
      "merchantTotalReported": 0,
      "merchantSnapshotFile": "",
      "lastReviewed": "2026-07-03",
      "nextAction": "Verify whether new affiliate applications are open before adding banners.",
      "notes": "Good content fit, but gate behind manual availability check."
    },
    {
      "id": "semrush-affiliates",
      "name": "Semrush Affiliate Program",
      "status": "candidate",
      "priority": "p1",
      "region": "GLOBAL",
      "network": "Semrush / Impact",
      "category": "seo_saas",
      "platformUrl": "https://www.semrush.com/lp/affiliate-program/en/",
      "homepageUrl": "https://www.semrush.com/lp/affiliate-program/en/",
      "applyUrl": "https://www.semrush.com/lp/affiliate-program/en/",
      "sourceUrl": "https://www.semrush.com/kb/97-affiliate-program",
      "countries": [
        "GLOBAL"
      ],
      "usedBySites": [],
      "usedByAppsInToss": [],
      "publicTrackingLabel": "semrush-affiliates",
      "disclosureRequired": true,
      "disclosureNote": "Affiliate disclosure required.",
      "monetizationModel": "Tracked links and creatives for SEO software referrals.",
      "payoutModel": "Fixed commissions for sale or trial activation; verify current table in Impact/Semrush.",
      "approvalDifficulty": "medium",
      "bannerSuitability": "medium",
      "deepLinkTemplate": "Use Semrush/Impact tracking links and creatives.",
      "contentFit": [
        "SEO guides",
        "marketing tools",
        "blog growth and analytics"
      ],
      "recommendedSlots": [
        "after-content-728x90",
        "sidebar-300x250"
      ],
      "allowedSites": [],
      "risk": "medium",
      "complianceNotes": [
        "Keep pricing/features current.",
        "Avoid guaranteed ranking claims."
      ],
      "merchantTotalReported": 0,
      "merchantSnapshotFile": "",
      "lastReviewed": "2026-07-03",
      "nextAction": "Map to SEO/content-ops sites and avoid hard ROI promises.",
      "notes": "High-intent fit for SEO/operator content."
    },
    {
      "id": "canva-canvassador",
      "name": "Canva Canvassador / Affiliate",
      "status": "candidate",
      "priority": "p2",
      "region": "GLOBAL",
      "network": "Canva",
      "category": "design_saas",
      "platformUrl": "https://www.canva.com/help/canva-affiliate-marketing-program/",
      "homepageUrl": "https://www.canva.com/help/canva-affiliate-marketing-program/",
      "applyUrl": "https://www.canva.com/help/canva-affiliate-marketing-program/",
      "sourceUrl": "https://www.canva.com/help/canva-affiliate-marketing-program/",
      "countries": [
        "GLOBAL"
      ],
      "usedBySites": [],
      "usedByAppsInToss": [],
      "publicTrackingLabel": "canva-canvassador",
      "disclosureRequired": true,
      "disclosureNote": "Affiliate disclosure required.",
      "monetizationModel": "Affiliate/ambassador referral for design users.",
      "payoutModel": "Verify current Canvassador/affiliate rewards after application.",
      "approvalDifficulty": "medium",
      "bannerSuitability": "medium",
      "deepLinkTemplate": "Use Canva-generated partner links.",
      "contentFit": [
        "design tools",
        "creator templates",
        "small business marketing"
      ],
      "recommendedSlots": [
        "after-content-728x90",
        "sidebar-300x250"
      ],
      "allowedSites": [],
      "risk": "medium",
      "complianceNotes": [
        "Use approved brand assets only.",
        "Do not publish old commission claims without verification."
      ],
      "merchantTotalReported": 0,
      "merchantSnapshotFile": "",
      "lastReviewed": "2026-07-03",
      "nextAction": "Apply where design/creator sites exist; verify current commission and asset rules.",
      "notes": "Good for creator and small-business content."
    },
    {
      "id": "grammarly-affiliates",
      "name": "Grammarly Affiliates",
      "status": "candidate",
      "priority": "p1",
      "region": "GLOBAL",
      "network": "Grammarly",
      "category": "writing_saas",
      "platformUrl": "https://www.grammarly.com/affiliates",
      "homepageUrl": "https://www.grammarly.com/affiliates",
      "applyUrl": "https://www.grammarly.com/affiliates",
      "sourceUrl": "https://www.grammarly.com/affiliates",
      "countries": [
        "GLOBAL"
      ],
      "usedBySites": [],
      "usedByAppsInToss": [],
      "publicTrackingLabel": "grammarly-affiliates",
      "disclosureRequired": true,
      "disclosureNote": "Affiliate disclosure required.",
      "monetizationModel": "Writing assistant referral links and creatives.",
      "payoutModel": "Commission structure varies by conversion type and performer tier; verify inside account.",
      "approvalDifficulty": "low",
      "bannerSuitability": "medium",
      "deepLinkTemplate": "Use Grammarly affiliate link/creative generated after approval.",
      "contentFit": [
        "English writing",
        "study",
        "business email",
        "AI productivity"
      ],
      "recommendedSlots": [
        "after-content-728x90",
        "mobile-inline-320x100"
      ],
      "allowedSites": [],
      "risk": "low",
      "complianceNotes": [
        "Keep feature claims current.",
        "Avoid representing the product as a replacement for professional advice."
      ],
      "merchantTotalReported": 0,
      "merchantSnapshotFile": "",
      "lastReviewed": "2026-07-03",
      "nextAction": "Use on English/AI/productivity sites with tutorial content.",
      "notes": "Fast SaaS candidate for English and productivity pages."
    },
    {
      "id": "ripplealba",
      "name": "RippleAlba",
      "status": "manual_review",
      "priority": "manual",
      "region": "KR",
      "network": "RippleAlba",
      "category": "affiliate_network",
      "platformUrl": "",
      "homepageUrl": "",
      "applyUrl": "",
      "sourceUrl": "data/monetization/affiliates/ripplealba-merchants.yml",
      "countries": [
        "KR"
      ],
      "usedBySites": [],
      "usedByAppsInToss": [],
      "publicTrackingLabel": "ripplealba",
      "disclosureRequired": true,
      "disclosureNote": "Affiliate/ad disclosure required.",
      "monetizationModel": "Captured merchant pool from prior manual input.",
      "payoutModel": "Varies by merchant; many offers require policy review.",
      "approvalDifficulty": "high",
      "bannerSuitability": "medium",
      "deepLinkTemplate": "Verify inside network before generating any public links.",
      "contentFit": [
        "campaign-specific CPA/CPS"
      ],
      "recommendedSlots": [
        "after-content-728x90"
      ],
      "allowedSites": [],
      "risk": "high",
      "complianceNotes": [
        "Current merchant snapshot contains encoding damage and empty merchant_entries.",
        "Sensitive categories such as finance, legal, health, insurance require strict manual review."
      ],
      "merchantTotalReported": 390,
      "merchantSnapshotFile": "affiliates/ripplealba-merchants.yml",
      "lastReviewed": "2026-07-03",
      "nextAction": "Re-capture merchant list in clean UTF-8 and reject sensitive/high-claim offers before banner use.",
      "notes": "Keep as legacy candidate source until clean merchant data is captured."
    }
  ],
  "affiliateItems": [
    {
      "id": "amazon-associates-primary",
      "programId": "amazon-associates",
      "title": "Amazon Associates monetization item",
      "status": "candidate",
      "priority": "p0",
      "region": "GLOBAL",
      "network": "Amazon",
      "category": "ecommerce",
      "payoutModel": "Category-based standard commission income on qualifying purchases; verify current rate table.",
      "approvalDifficulty": "medium",
      "bannerSuitability": "high",
      "contentFit": [
        "English product reviews",
        "software/hardware buying guides",
        "global shopping posts"
      ],
      "recommendedSlots": [
        "article-mid-728x90",
        "after-content-728x90",
        "mobile-inline-320x100"
      ],
      "allowedSites": [],
      "applyUrl": "https://affiliate-program.amazon.com/",
      "sourceUrl": "https://affiliate-program.amazon.com/help/operating/policies",
      "nextAction": "Apply with English/global sites and add required Amazon Associate disclosure text.",
      "risk": "medium",
      "complianceNotes": [
        "Do not cloak or alter Amazon links outside allowed tools.",
        "Display Amazon-required associate disclosure where applicable.",
        "Verify use of images/prices through approved tools/API."
      ]
    },
    {
      "id": "coupang-partners-primary",
      "programId": "coupang-partners",
      "title": "Coupang Partners monetization item",
      "status": "candidate",
      "priority": "p0",
      "region": "KR",
      "network": "Coupang",
      "category": "ecommerce",
      "payoutModel": "CPS; official guide has stated 3% on eligible transaction amount, but verify current category terms before publishing.",
      "approvalDifficulty": "low",
      "bannerSuitability": "high",
      "contentFit": [
        "shopping guides",
        "product reviews",
        "household, beauty, baby, electronics, seasonal deals"
      ],
      "recommendedSlots": [
        "article-mid-728x90",
        "after-content-728x90",
        "mobile-inline-320x100"
      ],
      "allowedSites": [],
      "applyUrl": "https://partners.coupang.com/",
      "sourceUrl": "https://partners.coupangcdn.com/partners-guide/partners-guide-20240716100922.pdf",
      "nextAction": "Apply or confirm existing account, create site/channel list, then create first product-review banner link.",
      "risk": "medium",
      "complianceNotes": [
        "Use clear Korean affiliate disclosure near each recommendation.",
        "Use rel=sponsored nofollow for links.",
        "Verify current commission, cookie, prohibited traffic, and API rules in the account."
      ]
    },
    {
      "id": "hubspot-affiliates-primary",
      "programId": "hubspot-affiliates",
      "title": "HubSpot Affiliate Program monetization item",
      "status": "candidate",
      "priority": "p0",
      "region": "GLOBAL",
      "network": "HubSpot",
      "category": "b2b_saas",
      "payoutModel": "Public program materials have described 30% recurring commission up to 12 months; verify current terms before publication.",
      "approvalDifficulty": "medium",
      "bannerSuitability": "high",
      "contentFit": [
        "CRM comparisons",
        "B2B marketing",
        "sales operations",
        "startup tooling"
      ],
      "recommendedSlots": [
        "sidebar-300x250",
        "after-content-728x90",
        "article-mid-728x90"
      ],
      "allowedSites": [],
      "applyUrl": "https://www.hubspot.com/partners/affiliates",
      "sourceUrl": "https://www.hubspot.com/company-news/hubspot-launches-its-revamped-affiliate-program",
      "nextAction": "Apply for B2B/software sites and prepare CRM comparison CTAs after approval.",
      "risk": "medium",
      "complianceNotes": [
        "Do not confuse affiliate program with HubSpot solutions partner status.",
        "Verify current recurring commission and paid-plan eligibility in account terms."
      ]
    },
    {
      "id": "grammarly-affiliates-primary",
      "programId": "grammarly-affiliates",
      "title": "Grammarly Affiliates monetization item",
      "status": "candidate",
      "priority": "p1",
      "region": "GLOBAL",
      "network": "Grammarly",
      "category": "writing_saas",
      "payoutModel": "Commission structure varies by conversion type and performer tier; verify inside account.",
      "approvalDifficulty": "low",
      "bannerSuitability": "medium",
      "contentFit": [
        "English writing",
        "study",
        "business email",
        "AI productivity"
      ],
      "recommendedSlots": [
        "after-content-728x90",
        "mobile-inline-320x100"
      ],
      "allowedSites": [],
      "applyUrl": "https://www.grammarly.com/affiliates",
      "sourceUrl": "https://www.grammarly.com/affiliates",
      "nextAction": "Use on English/AI/productivity sites with tutorial content.",
      "risk": "low",
      "complianceNotes": [
        "Keep feature claims current.",
        "Avoid representing the product as a replacement for professional advice."
      ]
    },
    {
      "id": "awin-primary",
      "programId": "awin",
      "title": "Awin monetization item",
      "status": "candidate",
      "priority": "p1",
      "region": "GLOBAL",
      "network": "Awin",
      "category": "affiliate_network",
      "payoutModel": "Varies by advertiser; publisher signup advertised as no cost.",
      "approvalDifficulty": "medium",
      "bannerSuitability": "high",
      "contentFit": [
        "commerce",
        "software",
        "fashion/lifestyle",
        "international content"
      ],
      "recommendedSlots": [
        "sidebar-300x250",
        "after-content-728x90"
      ],
      "allowedSites": [],
      "applyUrl": "https://www.awin.com/us/pricing/affiliate-partners",
      "sourceUrl": "https://www.awin.com/us/pricing/affiliate-partners",
      "nextAction": "Apply and map advertisers to site categories; treat ShareASale legacy programs under Awin where applicable.",
      "risk": "medium",
      "complianceNotes": [
        "Advertiser terms vary.",
        "Confirm whether each brand supports your country/site."
      ]
    },
    {
      "id": "booking-affiliates-primary",
      "programId": "booking-affiliates",
      "title": "Booking.com Affiliate Partner Program monetization item",
      "status": "candidate",
      "priority": "p1",
      "region": "GLOBAL",
      "network": "Booking.com / affiliate networks",
      "category": "travel",
      "payoutModel": "Commission on eligible completed travel bookings; exact rate/network terms vary.",
      "approvalDifficulty": "medium",
      "bannerSuitability": "high",
      "contentFit": [
        "travel guides",
        "city itineraries",
        "hotel comparisons"
      ],
      "recommendedSlots": [
        "after-content-728x90",
        "sidebar-300x250"
      ],
      "allowedSites": [],
      "applyUrl": "https://www.booking.com/affiliate-program/v2/index.html",
      "sourceUrl": "https://www.booking.com/affiliate-program/v2/index.html",
      "nextAction": "Use only on travel-intent sites/pages; configure city/deep-link templates per article.",
      "risk": "medium",
      "complianceNotes": [
        "Do not claim unavailable discounts.",
        "Use truthful availability/ranking language."
      ]
    },
    {
      "id": "cj-affiliate-primary",
      "programId": "cj-affiliate",
      "title": "CJ Affiliate monetization item",
      "status": "candidate",
      "priority": "p1",
      "region": "GLOBAL",
      "network": "CJ",
      "category": "affiliate_network",
      "payoutModel": "Varies by advertiser.",
      "approvalDifficulty": "high",
      "bannerSuitability": "high",
      "contentFit": [
        "established content sites",
        "shopping, finance-safe, software, travel"
      ],
      "recommendedSlots": [
        "sidebar-300x250",
        "after-content-728x90"
      ],
      "allowedSites": [],
      "applyUrl": "https://signup.cj.com/member/signup/publisher/",
      "sourceUrl": "https://www.cj.com/publisher",
      "nextAction": "Apply after preparing traffic proof and site category descriptions.",
      "risk": "medium",
      "complianceNotes": [
        "Expect advertiser-by-advertiser approval.",
        "Avoid unsupported coupon/voucher claims."
      ]
    },
    {
      "id": "coupang-influencers-primary",
      "programId": "coupang-influencers",
      "title": "Coupang Influencers monetization item",
      "status": "candidate",
      "priority": "p1",
      "region": "KR",
      "network": "Coupang",
      "category": "creator_commerce",
      "payoutModel": "Base commission plus time-limited promotions may apply; verify inside program.",
      "approvalDifficulty": "medium",
      "bannerSuitability": "medium",
      "contentFit": [
        "creator-style recommendations",
        "curated shopping lists",
        "social-friendly product collections"
      ],
      "recommendedSlots": [
        "after-content-728x90",
        "mobile-inline-320x100"
      ],
      "allowedSites": [],
      "applyUrl": "https://influencers.coupang.com/",
      "sourceUrl": "https://influencers.coupang.com/",
      "nextAction": "Verify eligibility and whether site-owned channels can use this program.",
      "risk": "medium",
      "complianceNotes": [
        "Use only approved channels and generated links.",
        "Verify promotion terms before showing bonus rates."
      ]
    },
    {
      "id": "ebay-partner-network-primary",
      "programId": "ebay-partner-network",
      "title": "eBay Partner Network monetization item",
      "status": "candidate",
      "priority": "p1",
      "region": "GLOBAL",
      "network": "eBay",
      "category": "ecommerce_marketplace",
      "payoutModel": "Percentage of qualifying transaction GMB by category; caps may apply.",
      "approvalDifficulty": "medium",
      "bannerSuitability": "medium",
      "contentFit": [
        "collectibles",
        "used/refurbished products",
        "parts, niche gear, comparison content"
      ],
      "recommendedSlots": [
        "article-mid-728x90",
        "after-content-728x90"
      ],
      "allowedSites": [],
      "applyUrl": "https://partnernetwork.ebay.com/",
      "sourceUrl": "https://partnernetwork.ebay.com/our-program/rate-card",
      "nextAction": "Apply for global shopping/niche product sites after Amazon/Coupang baseline.",
      "risk": "medium",
      "complianceNotes": [
        "Review rate caps and prohibited traffic.",
        "Avoid misleading discount/voucher claims."
      ]
    },
    {
      "id": "impact-marketplace-primary",
      "programId": "impact-marketplace",
      "title": "impact.com Marketplace monetization item",
      "status": "candidate",
      "priority": "p1",
      "region": "GLOBAL",
      "network": "impact.com",
      "category": "affiliate_network",
      "payoutModel": "Varies by advertiser contract.",
      "approvalDifficulty": "medium",
      "bannerSuitability": "high",
      "contentFit": [
        "software",
        "commerce",
        "finance-safe comparisons",
        "premium brand reviews"
      ],
      "recommendedSlots": [
        "sidebar-300x250",
        "after-content-728x90"
      ],
      "allowedSites": [],
      "applyUrl": "https://impact.com/partners/",
      "sourceUrl": "https://impact.com/partners/",
      "nextAction": "Create publisher profile and shortlist brands by site category.",
      "risk": "medium",
      "complianceNotes": [
        "Each advertiser has separate approval and promotional restrictions.",
        "Store advertiser IDs and terms before enabling banners."
      ]
    },
    {
      "id": "linkprice-primary",
      "programId": "linkprice",
      "title": "LinkPrice monetization item",
      "status": "candidate",
      "priority": "p1",
      "region": "KR",
      "network": "LinkPrice",
      "category": "affiliate_network",
      "payoutModel": "Varies by merchant and campaign; verify per offer.",
      "approvalDifficulty": "medium",
      "bannerSuitability": "high",
      "contentFit": [
        "shopping, travel, finance, education, subscription services",
        "Korea-focused comparison pages"
      ],
      "recommendedSlots": [
        "sidebar-300x250",
        "after-content-728x90"
      ],
      "allowedSites": [],
      "applyUrl": "https://www.linkprice.com/",
      "sourceUrl": "https://www.linkprice.com/",
      "nextAction": "Apply and export merchant list by site category; avoid high-risk finance/medical offers until review.",
      "risk": "medium",
      "complianceNotes": [
        "Merchant terms vary; collect landing URL, allowed media, and prohibited keywords.",
        "Be alert for impersonation/phishing warnings; only use official login/domain."
      ]
    },
    {
      "id": "naver-shopping-connect-primary",
      "programId": "naver-shopping-connect",
      "title": "Naver Shopping Connect monetization item",
      "status": "candidate",
      "priority": "p1",
      "region": "KR",
      "network": "Naver Brand Connect",
      "category": "ecommerce",
      "payoutModel": "Revenue-share set by participating sellers/products; verify each product offer.",
      "approvalDifficulty": "medium",
      "bannerSuitability": "medium",
      "contentFit": [
        "Naver-facing product recommendation",
        "beauty, living, parenting, food, local shopping"
      ],
      "recommendedSlots": [
        "article-mid-728x90",
        "mobile-inline-320x100"
      ],
      "allowedSites": [],
      "applyUrl": "https://brandconnect.naver.com/",
      "sourceUrl": "https://www.navercorp.com/media/pressReleasesDetail?seq=33116",
      "nextAction": "Confirm creator/channel eligibility and collect product-level revenue share.",
      "risk": "medium",
      "complianceNotes": [
        "Product-level terms vary by seller.",
        "Keep recommendation content specific to the product/store being promoted."
      ]
    },
    {
      "id": "partnerstack-marketplace-primary",
      "programId": "partnerstack-marketplace",
      "title": "PartnerStack Marketplace monetization item",
      "status": "candidate",
      "priority": "p1",
      "region": "GLOBAL",
      "network": "PartnerStack",
      "category": "b2b_saas",
      "payoutModel": "Varies by vendor; may include fixed bounty and/or revenue share.",
      "approvalDifficulty": "medium",
      "bannerSuitability": "medium",
      "contentFit": [
        "AI tools",
        "business software",
        "productivity",
        "marketing operations"
      ],
      "recommendedSlots": [
        "sidebar-300x250",
        "after-content-728x90"
      ],
      "allowedSites": [],
      "applyUrl": "https://market.partnerstack.com/",
      "sourceUrl": "https://partnerstack.com/",
      "nextAction": "Shortlist SaaS offers that match AI/business/tool sites.",
      "risk": "medium",
      "complianceNotes": [
        "Vendor programs can close or pause.",
        "Verify allowed bidding/email/coupon terms."
      ]
    },
    {
      "id": "semrush-affiliates-primary",
      "programId": "semrush-affiliates",
      "title": "Semrush Affiliate Program monetization item",
      "status": "candidate",
      "priority": "p1",
      "region": "GLOBAL",
      "network": "Semrush / Impact",
      "category": "seo_saas",
      "payoutModel": "Fixed commissions for sale or trial activation; verify current table in Impact/Semrush.",
      "approvalDifficulty": "medium",
      "bannerSuitability": "medium",
      "contentFit": [
        "SEO guides",
        "marketing tools",
        "blog growth and analytics"
      ],
      "recommendedSlots": [
        "after-content-728x90",
        "sidebar-300x250"
      ],
      "allowedSites": [],
      "applyUrl": "https://www.semrush.com/lp/affiliate-program/en/",
      "sourceUrl": "https://www.semrush.com/kb/97-affiliate-program",
      "nextAction": "Map to SEO/content-ops sites and avoid hard ROI promises.",
      "risk": "medium",
      "complianceNotes": [
        "Keep pricing/features current.",
        "Avoid guaranteed ranking claims."
      ]
    },
    {
      "id": "shopify-affiliates-primary",
      "programId": "shopify-affiliates",
      "title": "Shopify Affiliate Program monetization item",
      "status": "candidate",
      "priority": "p1",
      "region": "GLOBAL",
      "network": "Shopify",
      "category": "ecommerce_saas",
      "payoutModel": "Commission on eligible paid merchant referrals; verify current terms.",
      "approvalDifficulty": "medium",
      "bannerSuitability": "medium",
      "contentFit": [
        "online business",
        "smart seller",
        "ecommerce setup",
        "side-hustle guides"
      ],
      "recommendedSlots": [
        "after-content-728x90",
        "sidebar-300x250"
      ],
      "allowedSites": [],
      "applyUrl": "https://www.shopify.com/affiliates",
      "sourceUrl": "https://help.shopify.com/en/affiliates/about",
      "nextAction": "Match to seller/ecommerce sites and create tutorial CTAs.",
      "risk": "medium",
      "complianceNotes": [
        "Do not promise income outcomes.",
        "Use current plan/pricing facts only."
      ]
    },
    {
      "id": "canva-canvassador-primary",
      "programId": "canva-canvassador",
      "title": "Canva Canvassador / Affiliate monetization item",
      "status": "candidate",
      "priority": "p2",
      "region": "GLOBAL",
      "network": "Canva",
      "category": "design_saas",
      "payoutModel": "Verify current Canvassador/affiliate rewards after application.",
      "approvalDifficulty": "medium",
      "bannerSuitability": "medium",
      "contentFit": [
        "design tools",
        "creator templates",
        "small business marketing"
      ],
      "recommendedSlots": [
        "after-content-728x90",
        "sidebar-300x250"
      ],
      "allowedSites": [],
      "applyUrl": "https://www.canva.com/help/canva-affiliate-marketing-program/",
      "sourceUrl": "https://www.canva.com/help/canva-affiliate-marketing-program/",
      "nextAction": "Apply where design/creator sites exist; verify current commission and asset rules.",
      "risk": "medium",
      "complianceNotes": [
        "Use approved brand assets only.",
        "Do not publish old commission claims without verification."
      ]
    },
    {
      "id": "rakuten-advertising-primary",
      "programId": "rakuten-advertising",
      "title": "Rakuten Advertising monetization item",
      "status": "candidate",
      "priority": "p2",
      "region": "GLOBAL",
      "network": "Rakuten Advertising",
      "category": "affiliate_network",
      "payoutModel": "Varies by advertiser.",
      "approvalDifficulty": "medium",
      "bannerSuitability": "high",
      "contentFit": [
        "premium brands",
        "shopping",
        "lifestyle",
        "global content"
      ],
      "recommendedSlots": [
        "sidebar-300x250",
        "after-content-728x90"
      ],
      "allowedSites": [],
      "applyUrl": "https://rakutenadvertising.com/publishers/",
      "sourceUrl": "https://pubhelp.rakutenadvertising.com/hc/en-us/articles/360059970591-Affiliate-Marketing-101-Video",
      "nextAction": "Apply after P0/P1 networks or where a target brand exists only on Rakuten.",
      "risk": "medium",
      "complianceNotes": [
        "Advertiser approvals and countries differ.",
        "Collect terms before enabling banners."
      ]
    },
    {
      "id": "notion-affiliates-primary",
      "programId": "notion-affiliates",
      "title": "Notion Affiliate Program monetization item",
      "status": "manual_review",
      "priority": "p2",
      "region": "GLOBAL",
      "network": "Notion / PartnerStack",
      "category": "productivity_saas",
      "payoutModel": "Official page states up to $50 per activated signup plus 20% of year-one revenue; verify current availability.",
      "approvalDifficulty": "high",
      "bannerSuitability": "medium",
      "contentFit": [
        "productivity templates",
        "AI workflow",
        "study/business organization"
      ],
      "recommendedSlots": [
        "after-content-728x90",
        "sidebar-300x250"
      ],
      "allowedSites": [],
      "applyUrl": "https://www.notion.com/affiliates",
      "sourceUrl": "https://www.notion.com/affiliates",
      "nextAction": "Verify whether new affiliate applications are open before adding banners.",
      "risk": "high",
      "complianceNotes": [
        "Program availability may change.",
        "Do not show payout claims unless verified in current application dashboard."
      ]
    },
    {
      "id": "tenping-primary",
      "programId": "tenping",
      "title": "Tenping monetization item",
      "status": "candidate",
      "priority": "p2",
      "region": "KR",
      "network": "Tenping",
      "category": "affiliate_network",
      "payoutModel": "Varies by campaign; verify offer terms before publication.",
      "approvalDifficulty": "medium",
      "bannerSuitability": "medium",
      "contentFit": [
        "viral content",
        "campaign-specific CPA offers",
        "SNS/blog mixed traffic"
      ],
      "recommendedSlots": [
        "after-content-728x90",
        "mobile-inline-320x100"
      ],
      "allowedSites": [],
      "applyUrl": "https://tenping.kr/",
      "sourceUrl": "https://tenping.kr/",
      "nextAction": "Use only after campaign compliance review and landing page quality check.",
      "risk": "high",
      "complianceNotes": [
        "CPA campaigns can carry aggressive claims; review copy manually.",
        "Do not use sensitive offers without legal/policy review."
      ]
    },
    {
      "id": "naver-adpost-primary",
      "programId": "naver-adpost",
      "title": "Naver AdPost monetization item",
      "status": "manual_review",
      "priority": "manual",
      "region": "KR",
      "network": "Naver",
      "category": "display_ads",
      "payoutModel": "Revenue share from ads shown/clicked on eligible Naver media; criteria are controlled by Naver.",
      "approvalDifficulty": "high",
      "bannerSuitability": "low",
      "contentFit": [
        "Naver Blog/Cafe media",
        "Naver ecosystem content"
      ],
      "recommendedSlots": [],
      "allowedSites": [],
      "applyUrl": "https://adpost.naver.com/",
      "sourceUrl": "https://help.naver.com/support/contents/contents.help?categoryNo=9418&serviceNo=726",
      "nextAction": "Track as a Naver media monetization option, but do not wire into banner redirects.",
      "risk": "high",
      "complianceNotes": [
        "Keep separate from affiliate link management.",
        "Eligibility and revenue share are platform-controlled."
      ]
    },
    {
      "id": "naver-brand-connect-primary",
      "programId": "naver-brand-connect",
      "title": "Naver Brand Connect monetization item",
      "status": "manual_review",
      "priority": "manual",
      "region": "KR",
      "network": "Naver Brand Connect",
      "category": "creator_campaigns",
      "payoutModel": "Campaign or negotiated settlement; verify per campaign before publishing.",
      "approvalDifficulty": "high",
      "bannerSuitability": "low",
      "contentFit": [
        "creator collaborations",
        "sponsored editorial",
        "Naver Blog, Instagram, YouTube channel campaigns"
      ],
      "recommendedSlots": [
        "after-content-728x90"
      ],
      "allowedSites": [],
      "applyUrl": "https://brandconnect.naver.com/",
      "sourceUrl": "https://help.naver.com/service/30027/contents/23408?lang=ko&osType=COMMONOS",
      "nextAction": "Keep as manual-review campaign source; do not wire as a normal banner affiliate until campaign terms are approved.",
      "risk": "high",
      "complianceNotes": [
        "Not a general self-serve affiliate network for every owned site.",
        "Each campaign can define channel, wording, and settlement restrictions."
      ]
    },
    {
      "id": "naver-shopping-live-primary",
      "programId": "naver-shopping-live",
      "title": "Naver Shopping Live Partnership monetization item",
      "status": "manual_review",
      "priority": "manual",
      "region": "KR",
      "network": "Naver",
      "category": "live_commerce",
      "payoutModel": "Negotiated per live event or campaign; verify manually.",
      "approvalDifficulty": "high",
      "bannerSuitability": "low",
      "contentFit": [
        "launch events",
        "seasonal live deals",
        "brand collaboration pages"
      ],
      "recommendedSlots": [
        "after-content-728x90"
      ],
      "allowedSites": [],
      "applyUrl": "https://help.naver.com/service/21349/contents/14569?lang=ko",
      "sourceUrl": "https://help.naver.com/service/21349/contents/14570?lang=ko",
      "nextAction": "Treat as proposal-only monetization; create banners only after event approval and date validation.",
      "risk": "high",
      "complianceNotes": [
        "Do not present as an open affiliate program.",
        "Remove or expire banners after event end dates."
      ]
    },
    {
      "id": "ripplealba-primary",
      "programId": "ripplealba",
      "title": "RippleAlba monetization item",
      "status": "manual_review",
      "priority": "manual",
      "region": "KR",
      "network": "RippleAlba",
      "category": "affiliate_network",
      "payoutModel": "Varies by merchant; many offers require policy review.",
      "approvalDifficulty": "high",
      "bannerSuitability": "medium",
      "contentFit": [
        "campaign-specific CPA/CPS"
      ],
      "recommendedSlots": [
        "after-content-728x90"
      ],
      "allowedSites": [],
      "applyUrl": "",
      "sourceUrl": "data/monetization/affiliates/ripplealba-merchants.yml",
      "nextAction": "Re-capture merchant list in clean UTF-8 and reject sensitive/high-claim offers before banner use.",
      "risk": "high",
      "complianceNotes": [
        "Current merchant snapshot contains encoding damage and empty merchant_entries.",
        "Sensitive categories such as finance, legal, health, insurance require strict manual review."
      ]
    }
  ],
  "playbook": {
    "disclosureTemplateKo": "이 글에는 제휴 링크가 포함될 수 있으며, 링크를 통한 구매 또는 가입 시 일정액의 수수료를 받을 수 있습니다.",
    "disclosureTemplateEn": "This content contains affiliate links. We may earn a commission when you buy or sign up through these links.",
    "defaultRel": "sponsored nofollow",
    "bannerSlotStrategy": [
      {
        "slot": "article-mid-728x90",
        "purpose": "Comparison/review articles after the first useful answer.",
        "fit": "Coupang, Amazon, eBay, Booking, SaaS trials"
      },
      {
        "slot": "sidebar-300x250",
        "purpose": "Evergreen tools and marketplace offers on desktop.",
        "fit": "SaaS, affiliate networks, shopping category offers"
      },
      {
        "slot": "after-content-728x90",
        "purpose": "Decision-stage CTA after the article has answered intent.",
        "fit": "High-intent product, travel, software, finance-safe lead offers"
      },
      {
        "slot": "mobile-inline-320x100",
        "purpose": "Low-height mobile placement for strong single offer.",
        "fit": "Coupang, Naver Shopping Connect, Amazon, Grammarly"
      }
    ],
    "priorityRules": [
      {
        "id": "p0",
        "rule": "Start with programs that match broad site inventory, allow links/banners, and have clear public onboarding."
      },
      {
        "id": "p1",
        "rule": "Use selective networks after site category pages, disclosure, and traffic proof are ready."
      },
      {
        "id": "manual",
        "rule": "Do not deploy until commission, approval status, and promotional restrictions are verified inside the account."
      }
    ]
  },
  "ripplealba": {
    "programId": "ripplealba",
    "programName": "리플알바",
    "merchantTotalReported": 390,
    "snapshotStartedAt": "2026-06-28",
    "snapshotStatus": "captured",
    "merchantEntryCount": 0,
    "categoriesSeen": [
      "광고/회원가입",
      "건강/다이어트",
      "개인회생/법률",
      "결혼",
      "기타",
      "대출/금융",
      "라이프",
      "렌트/리스",
      "로또",
      "보험/상조",
      "어린이/키성장",
      "여성/육아",
      "자격증/학원"
    ],
    "highValueCandidates": [
      {
        "category": "개인회생/법률",
        "name": "인공관절직업병보상센터",
        "commissionKrw": 200000,
        "previousMonthApplyRatePercent": null,
        "previousMonthApprovalRatePercent": null,
        "promotion": true,
        "priorityNote": "최고 단가지만 산출불가라 정책·전환 리스크 검토 필요."
      },
      {
        "category": "여성/육아",
        "name": "미즈케어 솔루션",
        "commissionKrw": 140000,
        "previousMonthApplyRatePercent": null,
        "previousMonthApprovalRatePercent": null,
        "promotion": true,
        "priorityNote": "고단가 반복 상품군. 승인율 정보가 없거나 낮은 변형이 있어 검증 필요."
      },
      {
        "category": "여성/육아",
        "name": "미즈케어 솔루션 2",
        "commissionKrw": 140000,
        "previousMonthApplyRatePercent": 2.68,
        "previousMonthApprovalRatePercent": 6.85,
        "promotion": true,
        "priorityNote": "고단가이나 승인율이 낮아 보수적으로 평가."
      },
      {
        "category": "개인회생/법률",
        "name": "직업병보상전문상담센터",
        "commissionKrw": 90000,
        "previousMonthApplyRatePercent": 2.49,
        "previousMonthApprovalRatePercent": 5.17,
        "promotion": true,
        "priorityNote": "고단가이나 승인율이 낮아 보수적으로 평가."
      },
      {
        "category": "건강/다이어트",
        "name": "신비감 플러스 다이어트",
        "commissionKrw": 76000,
        "previousMonthApplyRatePercent": 0.53,
        "previousMonthApprovalRatePercent": 54,
        "promotion": true,
        "priorityNote": "건강/다이어트 고단가 후보."
      },
      {
        "category": "개인회생/법률",
        "name": "부장검사 출신 개인회생 법률사무소 청하",
        "commissionKrw": 72000,
        "previousMonthApplyRatePercent": null,
        "previousMonthApprovalRatePercent": null,
        "promotion": true,
        "priorityNote": "법률 고단가 후보."
      },
      {
        "category": "개인회생/법률",
        "name": "부장검사 출신 개인회생 법률사무소 청하 2",
        "commissionKrw": 72000,
        "previousMonthApplyRatePercent": 1.15,
        "previousMonthApprovalRatePercent": 62.5,
        "promotion": true,
        "priorityNote": "법률 고단가 후보. 승인율은 중간 수준."
      },
      {
        "category": "개인회생/법률",
        "name": "개인회생법률상담센터 동윤",
        "commissionKrw": 70000,
        "previousMonthApplyRatePercent": 0.61,
        "previousMonthApprovalRatePercent": 12.2,
        "promotion": true,
        "priorityNote": "고단가이나 승인율 낮음."
      },
      {
        "category": "개인회생/법률",
        "name": "변호사이정용법률사무소",
        "commissionKrw": 70000,
        "previousMonthApplyRatePercent": null,
        "previousMonthApprovalRatePercent": null,
        "promotion": true,
        "priorityNote": "법률 고단가 후보."
      },
      {
        "category": "개인회생/법률",
        "name": "법무법인서울 디딤돌 회생파산센터",
        "commissionKrw": 65000,
        "previousMonthApplyRatePercent": null,
        "previousMonthApprovalRatePercent": null,
        "promotion": false,
        "priorityNote": "반복 노출된 법률 고단가 후보."
      },
      {
        "category": "건강/다이어트",
        "name": "삼성제약 혈당+눈건강 솔루션 골드 2-4",
        "commissionKrw": 64000,
        "previousMonthApplyRatePercent": 1.6,
        "previousMonthApprovalRatePercent": 88.37,
        "promotion": true,
        "priorityNote": "고단가와 높은 승인율을 모두 가진 우선 검토 후보."
      },
      {
        "category": "건강/다이어트",
        "name": "삼성제약 혈당+눈건강 솔루션 골드 2-1",
        "commissionKrw": 64000,
        "previousMonthApplyRatePercent": 2.56,
        "previousMonthApprovalRatePercent": 82.86,
        "promotion": true,
        "priorityNote": "고단가와 높은 승인율을 모두 가진 우선 검토 후보."
      },
      {
        "category": "건강/다이어트",
        "name": "삼성제약 바로쾌변 프리미엄 골드 6",
        "commissionKrw": 64000,
        "previousMonthApplyRatePercent": 2.54,
        "previousMonthApprovalRatePercent": 77.14,
        "promotion": true,
        "priorityNote": "고단가 후보."
      },
      {
        "category": "건강/다이어트",
        "name": "호관원 프리미엄 골드",
        "commissionKrw": 64000,
        "previousMonthApplyRatePercent": 1.62,
        "previousMonthApprovalRatePercent": 75,
        "promotion": true,
        "priorityNote": "고단가 후보."
      },
      {
        "category": "건강/다이어트",
        "name": "코로솔린",
        "commissionKrw": 64000,
        "previousMonthApplyRatePercent": 2.07,
        "previousMonthApprovalRatePercent": 54.35,
        "promotion": true,
        "priorityNote": "고단가이나 승인율 중간 이하."
      },
      {
        "category": "대출/금융",
        "name": "주식자금대출 하이스탁론",
        "commissionKrw": 61000,
        "previousMonthApplyRatePercent": 3.48,
        "previousMonthApprovalRatePercent": 70.43,
        "promotion": true,
        "priorityNote": "금융 고단가 후보. 정책 리스크 검토 필요."
      },
      {
        "category": "대출/금융",
        "name": "국내해외ETF 주식담보대출 올타임스탁론",
        "commissionKrw": 61000,
        "previousMonthApplyRatePercent": null,
        "previousMonthApprovalRatePercent": null,
        "promotion": true,
        "priorityNote": "금융 고단가 후보. 정책 리스크 검토 필요."
      },
      {
        "category": "개인회생/법률",
        "name": "법무법인 서앤율",
        "commissionKrw": 60000,
        "previousMonthApplyRatePercent": 0.8,
        "previousMonthApprovalRatePercent": 94.23,
        "promotion": true,
        "priorityNote": "고단가와 높은 승인율을 모두 가진 우선 검토 후보."
      }
    ],
    "currentCaptureSummary": {
      "status": "사용자가 리플알바 머천트 목록 제공을 종료함.",
      "next_action": "이번 입력분을 기준으로 고단가, 고승인율, 고신청률, 정책리스크별 실행 후보를 선정한다.",
      "capture_closed_at": "2026-06-28",
      "captured_scope_note": "리플알바 전체 390개 머천트 중 사용자가 대화로 제공한 목록 스냅샷. 일부 상품은 반복 노출되었고 일부 지표는 산출불가 또는 0으로 제공됨.",
      "known_repeated_names": [
        "다타랩",
        "동경건설 철거",
        "동성바이오",
        "더복력",
        "더복력 2",
        "무촌철거 1등 철거 플랫폼",
        "법무법인서울 디딤돌 회생파산센터",
        "백세청윤",
        "부산 라모르 웨딩박람회",
        "분양해지부동산상담 법무법인서앤율",
        "삼성제약 바로쾌변 프리미엄 골드 6",
        "삼성제약 혈당+눈건강 솔루션 골드 2-4",
        "서울 롯데월드타워 대형 웨딩박람회",
        "인터넷팡팡",
        "주식자금대출 하이스탁론",
        "코로솔린",
        "탈젠플러스",
        "혈당케어의 중심 진잠원",
        "호관원 프리미엄 골드"
      ]
    },
    "priorityRules": [
      {
        "id": "high_commission",
        "rule": "승인시 60000원 이상이면 고단가 후보로 분류한다."
      },
      {
        "id": "high_approval",
        "rule": "전월승인율 80% 이상이면 승인 안정 후보로 분류한다."
      },
      {
        "id": "high_apply",
        "rule": "전월신청률 5% 이상이면 수요 신호가 있는 후보로 분류한다."
      },
      {
        "id": "no_rate",
        "rule": "산출불가 항목은 신규/저표본 후보로 보고 단가와 카테고리 적합성만 우선 평가한다."
      },
      {
        "id": "sensitive_category",
        "rule": "대출/금융, 보험/상조, 개인회생/법률, 건강/다이어트는 과장 표현과 정책 리스크를 별도 검토한다."
      }
    ]
  }
}
